odoo8_addon_account_invoice_supplierinfo_update_variant-8.0.1.0.0.99.dev6-py2.7-nspkg.pth
odoo8_addon_account_invoice_supplierinfo_update_variant-8.0.1.0.0.99.dev6.dist-info/DESCRIPTION.rst
odoo8_addon_account_invoice_supplierinfo_update_variant-8.0.1.0.0.99.dev6.dist-info/METADATA
odoo8_addon_account_invoice_supplierinfo_update_variant-8.0.1.0.0.99.dev6.dist-info/RECORD
odoo8_addon_account_invoice_supplierinfo_update_variant-8.0.1.0.0.99.dev6.dist-info/WHEEL
odoo8_addon_account_invoice_supplierinfo_update_variant-8.0.1.0.0.99.dev6.dist-info/metadata.json
odoo8_addon_account_invoice_supplierinfo_update_variant-8.0.1.0.0.99.dev6.dist-info/namespace_packages.txt
odoo8_addon_account_invoice_supplierinfo_update_variant-8.0.1.0.0.99.dev6.dist-info/top_level.txt
odoo_addons/account_invoice_supplierinfo_update_variant/README.rst
odoo_addons/account_invoice_supplierinfo_update_variant/__init__.py
odoo_addons/account_invoice_supplierinfo_update_variant/__openerp__.py
odoo_addons/account_invoice_supplierinfo_update_variant/demo/account_invoice.xml
odoo_addons/account_invoice_supplierinfo_update_variant/i18n/ar.po
odoo_addons/account_invoice_supplierinfo_update_variant/i18n/bs.po
odoo_addons/account_invoice_supplierinfo_update_variant/i18n/ca.po
odoo_addons/account_invoice_supplierinfo_update_variant/i18n/cs.po
odoo_addons/account_invoice_supplierinfo_update_variant/i18n/de.po
odoo_addons/account_invoice_supplierinfo_update_variant/i18n/en_GB.po
odoo_addons/account_invoice_supplierinfo_update_variant/i18n/es.po
odoo_addons/account_invoice_supplierinfo_update_variant/i18n/es_CR.po
odoo_addons/account_invoice_supplierinfo_update_variant/i18n/es_EC.po
odoo_addons/account_invoice_supplierinfo_update_variant/i18n/es_MX.po
odoo_addons/account_invoice_supplierinfo_update_variant/i18n/et.po
odoo_addons/account_invoice_supplierinfo_update_variant/i18n/fr.po
odoo_addons/account_invoice_supplierinfo_update_variant/i18n/fr_CH.po
odoo_addons/account_invoice_supplierinfo_update_variant/i18n/hr.po
odoo_addons/account_invoice_supplierinfo_update_variant/i18n/hu.po
odoo_addons/account_invoice_supplierinfo_update_variant/i18n/it.po
odoo_addons/account_invoice_supplierinfo_update_variant/i18n/ja.po
odoo_addons/account_invoice_supplierinfo_update_variant/i18n/lt.po
odoo_addons/account_invoice_supplierinfo_update_variant/i18n/mk.po
odoo_addons/account_invoice_supplierinfo_update_variant/i18n/mn.po
odoo_addons/account_invoice_supplierinfo_update_variant/i18n/nb.po
odoo_addons/account_invoice_supplierinfo_update_variant/i18n/nl.po
odoo_addons/account_invoice_supplierinfo_update_variant/i18n/nl_BE.po
