Metadata-Version: 2.0
Name: odoo8-addon-account-invoice-supplierinfo-update-variant
Version: 8.0.1.0.0.99.dev6
Summary: In the supplier invoice, automatically update all products variants whose unit price on the line is different from the supplier price
Home-page: http://akretion.com
Author: Akretion, Odoo Community Association (OCA)
Author-email: support@odoo-community.org
License: AGPL-3
Platform: UNKNOWN
Classifier: Programming Language :: Python :: 2.7
Classifier: Framework :: Odoo
Classifier: License :: OSI Approved :: GNU Affero General Public License v3
Requires-Dist: odoo (<9.0a,>=8.0a)
Requires-Dist: odoo8-addon-account-invoice-supplierinfo-update
Requires-Dist: odoo8-addon-product-variant-supplierinfo
